{"featureCount":16,"formatVersion":1,"histograms":{"meta":[{"arrayParams":{"chunkSize":10000,"length":4,"urlTemplate":"hist-10000-{Chunk}.json"},"basesPerBin":"10000"}],"stats":[{"basesPerBin":"10000","max":6,"mean":4}]},"intervals":{"classes":[{"attributes":["Start","End","Strand","Name","Seq_id"],"isArrayAttr":{}},{"attributes":["Start","End","Chunk"],"isArrayAttr":{"Sublist":1}}],"count":16,"lazyClass":1,"maxEnd":32272,"minStart":4723,"nclist":[[0,4723,4748,1,"match_part","Scaffold1168"],[0,4749,4898,1,"match_part","Scaffold1168"],[0,5105,5254,1,"match_part","Scaffold1168"],[0,5255,5280,1,"match_part","Scaffold1168"],[0,5280,5310,1,"match_part","Scaffold1168"],[0,5310,5435,1,"match_part","Scaffold1168"],[0,28039,28130,1,"match_part","Scaffold1168"],[0,28267,28403,1,"match_part","Scaffold1168"],[0,29663,29710,1,"match_part","Scaffold1168"],[0,29835,29895,1,"match_part","Scaffold1168"],[0,30087,30198,1,"match_part","Scaffold1168"],[0,30793,30959,1,"match_part","Scaffold1168"],[0,31004,31112,1,"match_part","Scaffold1168"],[0,31163,31271,1,"match_part","Scaffold1168"],[0,31865,31994,1,"match_part","Scaffold1168"],[0,32143,32272,1,"match_part","Scaffold1168"]],"urlTemplate":"lf-{Chunk}.json"}}