{"featureCount":11,"formatVersion":1,"histograms":{"meta":[{"arrayParams":{"chunkSize":10000,"length":4,"urlTemplate":"hist-2000-{Chunk}.json"},"basesPerBin":"2000"}],"stats":[{"basesPerBin":"2000","max":4,"mean":2.75}]},"intervals":{"classes":[{"attributes":["Start","End","Strand","Name","Seq_id"],"isArrayAttr":{}},{"attributes":["Start","End","Chunk"],"isArrayAttr":{"Sublist":1}}],"count":11,"lazyClass":1,"maxEnd":7694,"minStart":164,"nclist":[[0,164,364,-1,"match_part","Scaffold4189"],[0,986,1061,-1,"match_part","Scaffold4189"],[0,1244,1295,-1,"match_part","Scaffold4189"],[0,1835,1967,-1,"match_part","Scaffold4189"],[0,2912,2993,-1,"match_part","Scaffold4189"],[0,3458,3510,-1,"match_part","Scaffold4189"],[0,4132,4196,-1,"match_part","Scaffold4189"],[0,4741,4879,-1,"match_part","Scaffold4189"],[0,5356,5413,-1,"match_part","Scaffold4189"],[0,6001,6097,-1,"match_part","Scaffold4189"],[0,7638,7694,-1,"match_part","Scaffold4189"]],"urlTemplate":"lf-{Chunk}.json"}}