{"featureCount":36,"formatVersion":1,"histograms":{"meta":[{"arrayParams":{"chunkSize":10000,"length":10,"urlTemplate":"hist-2000-{Chunk}.json"},"basesPerBin":"2000"}],"stats":[{"basesPerBin":"2000","max":9,"mean":3.8}]},"intervals":{"classes":[{"attributes":["Start","End","Strand","Name","Seq_id"],"isArrayAttr":{}},{"attributes":["Start","End","Chunk"],"isArrayAttr":{"Sublist":1}}],"count":36,"lazyClass":1,"maxEnd":19445,"minStart":33,"nclist":[[0,33,112,1,"match_part","Scaffold1511"],[0,148,202,1,"match_part","Scaffold1511"],[0,222,227,1,"match_part","Scaffold1511"],[0,227,749,1,"match_part","Scaffold1511"],[0,912,1134,1,"match_part","Scaffold1511"],[0,1194,1248,1,"match_part","Scaffold1511"],[0,1389,1512,1,"match_part","Scaffold1511"],[0,1648,1796,1,"match_part","Scaffold1511"],[0,2020,2241,-1,"match_part","Scaffold1511"],[0,2462,2660,-1,"match_part","Scaffold1511"],[0,3035,3147,-1,"match_part","Scaffold1511"],[0,3414,3503,-1,"match_part","Scaffold1511"],[0,3730,3811,-1,"match_part","Scaffold1511"],[0,4311,4414,-1,"match_part","Scaffold1511"],[0,9897,10043,-1,"match_part","Scaffold1511"],[0,10502,10663,-1,"match_part","Scaffold1511"],[0,11098,11268,-1,"match_part","Scaffold1511"],[0,11757,11873,-1,"match_part","Scaffold1511"],[0,12447,12538,-1,"match_part","Scaffold1511"],[0,12867,13011,-1,"match_part","Scaffold1511"],[0,13653,13833,-1,"match_part","Scaffold1511"],[0,14050,14159,-1,"match_part","Scaffold1511"],[0,14505,14668,-1,"match_part","Scaffold1511"],[0,14993,15159,-1,"match_part","Scaffold1511"],[0,15451,15579,-1,"match_part","Scaffold1511"],[0,15958,16358,-1,"match_part","Scaffold1511"],[0,16359,16367,-1,"match_part","Scaffold1511"],[0,18260,18273,1,"match_part","Scaffold1511"],[0,18277,18409,1,"match_part","Scaffold1511"],[0,18316,18409,1,"match_part","Scaffold1511"],[0,18771,18820,1,"match_part","Scaffold1511"],[0,18771,18820,1,"match_part","Scaffold1511"],[0,18920,18988,1,"match_part","Scaffold1511"],[0,18920,18988,1,"match_part","Scaffold1511"],[0,18941,19445,1,"match_part","Scaffold1511",{"Sublist":[[0,19202,19318,1,"match_part","Scaffold1511"]]}]],"urlTemplate":"lf-{Chunk}.json"}}