{"featureCount":160,"formatVersion":1,"histograms":{"meta":[{"arrayParams":{"chunkSize":10000,"length":50,"urlTemplate":"hist-2000-{Chunk}.json"},"basesPerBin":"2000"}],"stats":[{"basesPerBin":"2000","max":11,"mean":3.28}]},"intervals":{"classes":[{"attributes":["Start","End","Strand","Name","Seq_id"],"isArrayAttr":{}},{"attributes":["Start","End","Chunk"],"isArrayAttr":{"Sublist":1}}],"count":160,"lazyClass":1,"maxEnd":98565,"minStart":5360,"nclist":[[0,5360,5429,-1,"match_part","Scaffold405"],[0,5429,5450,-1,"match_part","Scaffold405"],[0,5450,5637,-1,"match_part","Scaffold405"],[0,5637,5641,-1,"match_part","Scaffold405"],[0,6149,6159,-1,"match_part","Scaffold405"],[0,6162,6255,-1,"match_part","Scaffold405"],[0,6255,6263,-1,"match_part","Scaffold405"],[0,6265,6286,-1,"match_part","Scaffold405"],[0,6343,6434,-1,"match_part","Scaffold405"],[0,6435,6458,-1,"match_part","Scaffold405"],[0,6460,6680,-1,"match_part","Scaffold405"],[0,6889,7000,-1,"match_part","Scaffold405"],[0,7218,7383,-1,"match_part","Scaffold405"],[0,7695,7860,-1,"match_part","Scaffold405"],[0,7955,8087,-1,"match_part","Scaffold405"],[0,8170,8332,-1,"match_part","Scaffold405"],[0,8427,8463,-1,"match_part","Scaffold405"],[0,8566,8690,-1,"match_part","Scaffold405"],[0,8792,8914,-1,"match_part","Scaffold405"],[0,9006,9117,-1,"match_part","Scaffold405"],[0,9198,9385,-1,"match_part","Scaffold405"],[0,11184,11245,-1,"match_part","Scaffold405"],[0,11245,11449,-1,"match_part","Scaffold405"],[0,11449,11556,-1,"match_part","Scaffold405"],[0,12021,12148,-1,"match_part","Scaffold405"],[0,12885,13001,-1,"match_part","Scaffold405"],[0,13536,13664,-1,"match_part","Scaffold405"],[0,13865,13989,-1,"match_part","Scaffold405"],[0,14439,14570,-1,"match_part","Scaffold405"],[0,14933,15048,-1,"match_part","Scaffold405"],[0,15489,15614,-1,"match_part","Scaffold405"],[0,15878,15978,-1,"match_part","Scaffold405"],[0,16489,16617,-1,"match_part","Scaffold405"],[0,16904,17007,-1,"match_part","Scaffold405"],[0,17718,17891,-1,"match_part","Scaffold405"],[0,18428,18538,-1,"match_part","Scaffold405"],[0,19204,19306,-1,"match_part","Scaffold405"],[0,19405,19473,-1,"match_part","Scaffold405"],[0,19573,19723,-1,"match_part","Scaffold405"],[0,19859,19965,-1,"match_part","Scaffold405"],[0,20246,20324,-1,"match_part","Scaffold405"],[0,20399,20455,-1,"match_part","Scaffold405"],[0,21684,21924,-1,"match_part","Scaffold405"],[0,21925,21962,-1,"match_part","Scaffold405"],[0,22281,22360,-1,"match_part","Scaffold405"],[0,22613,22680,-1,"match_part","Scaffold405"],[0,22790,22900,-1,"match_part","Scaffold405"],[0,23241,23265,-1,"match_part","Scaffold405"],[0,23265,23315,-1,"match_part","Scaffold405"],[0,23776,23890,-1,"match_part","Scaffold405"],[0,24033,24201,-1,"match_part","Scaffold405"],[0,24903,25029,-1,"match_part","Scaffold405"],[0,25306,26001,-1,"match_part","Scaffold405"],[0,26089,26165,-1,"match_part","Scaffold405"],[0,26569,26733,-1,"match_part","Scaffold405"],[0,27100,27164,-1,"match_part","Scaffold405"],[0,27264,27464,-1,"match_part","Scaffold405"],[0,27701,27858,-1,"match_part","Scaffold405"],[0,28210,28596,-1,"match_part","Scaffold405"],[0,28820,28926,-1,"match_part","Scaffold405"],[0,29151,29264,-1,"match_part","Scaffold405"],[0,29708,29806,-1,"match_part","Scaffold405"],[0,30571,30611,-1,"match_part","Scaffold405"],[0,30710,30960,-1,"match_part","Scaffold405"],[0,31100,31195,-1,"match_part","Scaffold405"],[0,31405,31479,-1,"match_part","Scaffold405"],[0,32261,32374,-1,"match_part","Scaffold405"],[0,32616,32684,-1,"match_part","Scaffold405"],[0,32867,32941,-1,"match_part","Scaffold405"],[0,33015,33085,-1,"match_part","Scaffold405"],[0,33167,33261,-1,"match_part","Scaffold405"],[0,33510,33613,-1,"match_part","Scaffold405"],[0,34173,34272,-1,"match_part","Scaffold405"],[0,34511,34576,-1,"match_part","Scaffold405"],[0,34671,34738,-1,"match_part","Scaffold405"],[0,34935,35029,-1,"match_part","Scaffold405"],[0,35297,35383,-1,"match_part","Scaffold405"],[0,36085,36140,-1,"match_part","Scaffold405"],[0,36290,36361,-1,"match_part","Scaffold405"],[0,36469,36534,-1,"match_part","Scaffold405"],[0,36737,36789,-1,"match_part","Scaffold405"],[0,37215,37247,1,"match_part","Scaffold405"],[0,37638,37692,1,"match_part","Scaffold405"],[0,37834,37921,1,"match_part","Scaffold405"],[0,39303,39390,1,"match_part","Scaffold405"],[0,39559,39652,1,"match_part","Scaffold405"],[0,39875,40010,1,"match_part","Scaffold405"],[0,40249,40322,1,"match_part","Scaffold405"],[0,40416,40541,1,"match_part","Scaffold405"],[0,40975,41104,1,"match_part","Scaffold405"],[0,41749,41807,1,"match_part","Scaffold405"],[0,41851,41920,1,"match_part","Scaffold405"],[0,42221,42352,1,"match_part","Scaffold405"],[0,42802,42883,1,"match_part","Scaffold405"],[0,49479,49597,-1,"match_part","Scaffold405"],[0,49816,49910,-1,"match_part","Scaffold405"],[0,50410,50436,-1,"match_part","Scaffold405"],[0,53069,53246,1,"match_part","Scaffold405"],[0,53246,53346,1,"match_part","Scaffold405"],[0,53387,53530,1,"match_part","Scaffold405"],[0,54150,54340,1,"match_part","Scaffold405"],[0,54685,54710,1,"match_part","Scaffold405"],[0,54714,54725,1,"match_part","Scaffold405"],[0,62721,62859,1,"match_part","Scaffold405"],[0,64185,64387,1,"match_part","Scaffold405"],[0,64388,64395,1,"match_part","Scaffold405"],[0,64596,64719,1,"match_part","Scaffold405"],[0,65024,65314,1,"match_part","Scaffold405"],[0,65317,65524,1,"match_part","Scaffold405"],[0,65682,65827,1,"match_part","Scaffold405"],[0,65873,65957,1,"match_part","Scaffold405"],[0,66053,66176,1,"match_part","Scaffold405"],[0,66225,66409,1,"match_part","Scaffold405"],[0,66457,66590,1,"match_part","Scaffold405"],[0,66636,66695,1,"match_part","Scaffold405"],[0,66744,66978,1,"match_part","Scaffold405"],[0,67484,67552,1,"match_part","Scaffold405"],[0,67611,67734,1,"match_part","Scaffold405"],[0,67813,67930,1,"match_part","Scaffold405"],[0,68231,68433,1,"match_part","Scaffold405"],[0,68754,68904,1,"match_part","Scaffold405"],[0,69195,69289,1,"match_part","Scaffold405"],[0,69467,69574,1,"match_part","Scaffold405"],[0,70312,70496,1,"match_part","Scaffold405"],[0,70977,71146,1,"match_part","Scaffold405"],[0,71278,71356,1,"match_part","Scaffold405"],[0,71528,71645,1,"match_part","Scaffold405"],[0,71844,71981,1,"match_part","Scaffold405"],[0,72190,72317,1,"match_part","Scaffold405"],[0,72991,73570,1,"match_part","Scaffold405"],[0,73775,73941,1,"match_part","Scaffold405"],[0,75264,75278,1,"match_part","Scaffold405"],[0,75547,75612,1,"match_part","Scaffold405"],[0,75970,76128,1,"match_part","Scaffold405"],[0,76352,76434,1,"match_part","Scaffold405"],[0,76499,76624,1,"match_part","Scaffold405"],[0,77066,77201,1,"match_part","Scaffold405"],[0,79689,79927,1,"match_part","Scaffold405"],[0,84342,84390,1,"match_part","Scaffold405"],[0,85077,85193,1,"match_part","Scaffold405"],[0,85378,85504,1,"match_part","Scaffold405"],[0,85774,85884,1,"match_part","Scaffold405"],[0,86439,86571,1,"match_part","Scaffold405"],[0,86713,86763,1,"match_part","Scaffold405"],[0,87418,87560,1,"match_part","Scaffold405"],[0,88683,88788,1,"match_part","Scaffold405"],[0,89446,89518,1,"match_part","Scaffold405"],[0,89855,89926,1,"match_part","Scaffold405"],[0,91123,91241,1,"match_part","Scaffold405"],[0,91722,91923,1,"match_part","Scaffold405"],[0,92843,93107,1,"match_part","Scaffold405"],[0,93540,93619,1,"match_part","Scaffold405"],[0,94138,94220,1,"match_part","Scaffold405"],[0,94959,95030,1,"match_part","Scaffold405"],[0,95195,95320,1,"match_part","Scaffold405"],[0,97237,97352,-1,"match_part","Scaffold405"],[0,97470,97562,-1,"match_part","Scaffold405"],[0,97736,97841,-1,"match_part","Scaffold405"],[0,98121,98142,-1,"match_part","Scaffold405"],[0,98452,98565,-1,"match_part","Scaffold405"]],"urlTemplate":"lf-{Chunk}.json"}}