{"featureCount":50,"formatVersion":1,"histograms":{"meta":[{"arrayParams":{"chunkSize":10000,"length":11,"urlTemplate":"hist-5000-{Chunk}.json"},"basesPerBin":"5000"}],"stats":[{"basesPerBin":"5000","max":13,"mean":4.72727272727273}]},"intervals":{"classes":[{"attributes":["Start","End","Strand","Name","Seq_id"],"isArrayAttr":{}},{"attributes":["Start","End","Chunk"],"isArrayAttr":{"Sublist":1}}],"count":50,"lazyClass":1,"maxEnd":51824,"minStart":6253,"nclist":[[0,6253,6317,-1,"match_part","Scaffold758"],[0,6319,6348,-1,"match_part","Scaffold758"],[0,6348,6951,-1,"match_part","Scaffold758"],[0,7142,7550,-1,"match_part","Scaffold758"],[0,7724,8251,-1,"match_part","Scaffold758"],[0,8543,8659,1,"match_part","Scaffold758"],[0,8782,9846,1,"match_part","Scaffold758"],[0,9895,9981,1,"match_part","Scaffold758"],[0,10069,10614,1,"match_part","Scaffold758"],[0,10664,10776,1,"match_part","Scaffold758"],[0,11534,11745,1,"match_part","Scaffold758"],[0,12415,12462,1,"match_part","Scaffold758"],[0,13208,13332,1,"match_part","Scaffold758"],[0,13333,13427,1,"match_part","Scaffold758"],[0,13658,13749,1,"match_part","Scaffold758"],[0,14498,14556,1,"match_part","Scaffold758"],[0,14993,15124,1,"match_part","Scaffold758"],[0,15291,15394,1,"match_part","Scaffold758"],[0,15592,15693,1,"match_part","Scaffold758"],[0,15931,15967,1,"match_part","Scaffold758"],[0,16029,16129,1,"match_part","Scaffold758"],[0,16129,16142,1,"match_part","Scaffold758"],[0,17107,17122,1,"match_part","Scaffold758"],[0,17189,17246,1,"match_part","Scaffold758"],[0,17293,17414,1,"match_part","Scaffold758"],[0,18404,18431,1,"match_part","Scaffold758"],[0,18587,18733,1,"match_part","Scaffold758"],[0,18739,18779,1,"match_part","Scaffold758"],[0,18780,18797,1,"match_part","Scaffold758"],[0,28500,28728,-1,"match_part","Scaffold758"],[0,28780,28997,-1,"match_part","Scaffold758"],[0,29124,29243,-1,"match_part","Scaffold758"],[0,29726,29832,-1,"match_part","Scaffold758"],[0,30282,30410,-1,"match_part","Scaffold758"],[0,31327,31433,-1,"match_part","Scaffold758"],[0,31807,31871,-1,"match_part","Scaffold758"],[0,32689,32814,-1,"match_part","Scaffold758"],[0,33849,33952,-1,"match_part","Scaffold758"],[0,34888,35010,-1,"match_part","Scaffold758"],[0,36111,36217,-1,"match_part","Scaffold758"],[0,36690,36812,-1,"match_part","Scaffold758"],[0,47380,47555,-1,"match_part","Scaffold758"],[0,47630,47766,-1,"match_part","Scaffold758"],[0,47903,48015,-1,"match_part","Scaffold758"],[0,48895,48956,-1,"match_part","Scaffold758"],[0,49687,49738,-1,"match_part","Scaffold758"],[0,50206,50284,-1,"match_part","Scaffold758"],[0,50486,50537,-1,"match_part","Scaffold758"],[0,50894,51008,-1,"match_part","Scaffold758"],[0,51687,51824,-1,"match_part","Scaffold758"]],"urlTemplate":"lf-{Chunk}.json"}}