{"featureCount":9,"formatVersion":1,"histograms":{"meta":[{"arrayParams":{"chunkSize":10000,"length":3,"urlTemplate":"hist-2000-{Chunk}.json"},"basesPerBin":"2000"}],"stats":[{"basesPerBin":"2000","max":5,"mean":3}]},"intervals":{"classes":[{"attributes":["Start","End","Strand","Name","Seq_id"],"isArrayAttr":{}},{"attributes":["Start","End","Chunk"],"isArrayAttr":{"Sublist":1}}],"count":9,"lazyClass":1,"maxEnd":5251,"minStart":45,"nclist":[[0,45,183,1,"match_part","Scaffold5864"],[0,454,588,1,"match_part","Scaffold5864"],[0,809,818,1,"match_part","Scaffold5864"],[0,1106,1149,1,"match_part","Scaffold5864"],[0,1149,1361,1,"match_part","Scaffold5864"],[0,2326,2493,1,"match_part","Scaffold5864"],[0,2759,2872,1,"match_part","Scaffold5864"],[0,3401,3563,1,"match_part","Scaffold5864"],[0,4812,5251,1,"match_part","Scaffold5864"]],"urlTemplate":"lf-{Chunk}.json"}}