{"featureCount":2,"formatVersion":1,"histograms":{"meta":[{"arrayParams":{"chunkSize":10000,"length":1,"urlTemplate":"hist-1000-{Chunk}.json"},"basesPerBin":"1000"}],"stats":[{"basesPerBin":"1000","max":2,"mean":2}]},"intervals":{"classes":[{"attributes":["Start","End","Strand","Name","Seq_id"],"isArrayAttr":{}},{"attributes":["Start","End","Chunk"],"isArrayAttr":{"Sublist":1}}],"count":2,"lazyClass":1,"maxEnd":459,"minStart":188,"nclist":[[0,188,384,-1,"match_part","Scaffold31931"],[0,414,459,-1,"match_part","Scaffold31931"]],"urlTemplate":"lf-{Chunk}.json"}}