{"featureCount":5,"formatVersion":1,"histograms":{"meta":[{"arrayParams":{"chunkSize":10000,"length":2,"urlTemplate":"hist-1000-{Chunk}.json"},"basesPerBin":"1000"}],"stats":[{"basesPerBin":"1000","max":4,"mean":3}]},"intervals":{"classes":[{"attributes":["Start","End","Strand","Name","Seq_id"],"isArrayAttr":{}},{"attributes":["Start","End","Chunk"],"isArrayAttr":{"Sublist":1}}],"count":5,"lazyClass":1,"maxEnd":1435,"minStart":297,"nclist":[[0,297,479,1,"match_part","Scaffold9920"],[0,532,633,1,"match_part","Scaffold9920"],[0,686,844,1,"match_part","Scaffold9920"],[0,875,1153,1,"match_part","Scaffold9920"],[0,1256,1435,1,"match_part","Scaffold9920"]],"urlTemplate":"lf-{Chunk}.json"}}