{"featureCount":9,"formatVersion":1,"histograms":{"meta":[{"arrayParams":{"chunkSize":10000,"length":3,"urlTemplate":"hist-2000-{Chunk}.json"},"basesPerBin":"2000"}],"stats":[{"basesPerBin":"2000","max":6,"mean":3.33333333333333}]},"intervals":{"classes":[{"attributes":["Start","End","Strand","Name","Seq_id"],"isArrayAttr":{}},{"attributes":["Start","End","Chunk"],"isArrayAttr":{"Sublist":1}}],"count":9,"lazyClass":1,"maxEnd":4365,"minStart":1152,"nclist":[[0,1152,1271,-1,"match_part","Scaffold5729"],[0,1553,1763,-1,"match_part","Scaffold5729"],[0,3242,3341,-1,"match_part","Scaffold5729"],[0,3459,3596,-1,"match_part","Scaffold5729"],[0,3600,3631,-1,"match_part","Scaffold5729"],[0,3629,3706,1,"match_part","Scaffold5729",{"Sublist":[[0,3634,3643,-1,"match_part","Scaffold5729"]]}],[0,3796,4022,1,"match_part","Scaffold5729"],[0,4199,4365,1,"match_part","Scaffold5729"]],"urlTemplate":"lf-{Chunk}.json"}}