{"featureCount":11,"formatVersion":1,"histograms":{"meta":[{"arrayParams":{"chunkSize":10000,"length":4,"urlTemplate":"hist-2000-{Chunk}.json"},"basesPerBin":"2000"}],"stats":[{"basesPerBin":"2000","max":5,"mean":3}]},"intervals":{"classes":[{"attributes":["Start","End","Strand","Name","Seq_id"],"isArrayAttr":{}},{"attributes":["Start","End","Chunk"],"isArrayAttr":{"Sublist":1}}],"count":11,"lazyClass":1,"maxEnd":6575,"minStart":2429,"nclist":[[0,2429,2587,1,"match_part","Scaffold3284"],[0,2852,3029,1,"match_part","Scaffold3284"],[0,3105,3181,1,"match_part","Scaffold3284"],[0,3431,3618,1,"match_part","Scaffold3284"],[0,3919,4046,1,"match_part","Scaffold3284"],[0,4293,4440,1,"match_part","Scaffold3284"],[0,4968,5073,1,"match_part","Scaffold3284"],[0,5366,5493,1,"match_part","Scaffold3284"],[0,5827,5950,1,"match_part","Scaffold3284"],[0,6262,6269,1,"match_part","Scaffold3284"],[0,6389,6575,1,"match_part","Scaffold3284"]],"urlTemplate":"lf-{Chunk}.json"}}