{"scaffold50808":{"prefix":[],"exact":[["Scaffold50808",294,"Scaffold50808",null,0,294,20000]]},"scaffold53505":{"prefix":[],"exact":[["Scaffold53505",279,"Scaffold53505",null,0,279,20000]]},"scaffold8881":{"prefix":[],"exact":[["Scaffold8881",1969,"Scaffold8881",null,0,1969,20000]]},"scaffold6647":{"prefix":["Scaffold66470","Scaffold66471","Scaffold66472","Scaffold66473","Scaffold66474","Scaffold66475","Scaffold66476","Scaffold66477","Scaffold66478","Scaffold66479"],"exact":[["Scaffold6647",3179,"Scaffold6647",null,0,3179,20000]]},"scaffold27453":{"exact":[["Scaffold27453",528,"Scaffold27453",null,0,528,20000]],"prefix":[]},"scaffold36544":{"exact":[["Scaffold36544",406,"Scaffold36544",null,0,406,20000]],"prefix":[]},"scaffold25338":{"exact":[["Scaffold25338",571,"Scaffold25338",null,0,571,20000]],"prefix":[]},"scaffold55786":{"prefix":[],"exact":[["Scaffold55786",267,"Scaffold55786",null,0,267,20000]]},"scaffold35849":{"exact":[["Scaffold35849",413,"Scaffold35849",null,0,413,20000]],"prefix":[]},"scaffold16001":{"prefix":[],"exact":[["Scaffold16001",879,"Scaffold16001",null,0,879,20000]]},"scaffold42412":{"prefix":[],"exact":[["Scaffold42412",353,"Scaffold42412",null,0,353,20000]]},"scaffold10282":{"exact":[["Scaffold10282",1513,"Scaffold10282",null,0,1513,20000]],"prefix":[]},"scaffold44691":{"exact":[["Scaffold44691",335,"Scaffold44691",null,0,335,20000]],"prefix":[]},"scaffold62157":{"prefix":[],"exact":[["Scaffold62157",237,"Scaffold62157",null,0,237,20000]]},"scaffold40379":{"prefix":[],"exact":[["Scaffold40379",369,"Scaffold40379",null,0,369,20000]]}}