{"scaffold305":{"exact":[["Scaffold305",121744,"Scaffold305",null,0,121744,20000]],"prefix":["Scaffold3050","Scaffold30500","Scaffold30501","Scaffold30502","Scaffold30503","Scaffold30504","Scaffold30505","Scaffold30506","Scaffold30507","Scaffold30508","Scaffold30509","Scaffold3051","Scaffold30510","Scaffold30511","Scaffold30512","Scaffold30513","Scaffold30514","Scaffold30515","Scaffold30516","Scaffold30517",{"hitLimit":1,"name":"too many matches"}]},"scaffold40771":{"prefix":[],"exact":[["Scaffold40771",366,"Scaffold40771",null,0,366,20000]]},"scaffold58045":{"prefix":[],"exact":[["Scaffold58045",256,"Scaffold58045",null,0,256,20000]]},"scaffold69417":{"prefix":[],"exact":[["Scaffold69417",207,"Scaffold69417",null,0,207,20000]]},"scaffold44299":{"prefix":[],"exact":[["Scaffold44299",338,"Scaffold44299",null,0,338,20000]]},"scaffold15904":{"exact":[["Scaffold15904",883,"Scaffold15904",null,0,883,20000]],"prefix":[]},"scaffold61852":{"exact":[["Scaffold61852",238,"Scaffold61852",null,0,238,20000]],"prefix":[]},"scaffold25730":{"exact":[["Scaffold25730",562,"Scaffold25730",null,0,562,20000]],"prefix":[]},"scaffold4524":{"exact":[["Scaffold4524",5517,"Scaffold4524",null,0,5517,20000]],"prefix":["Scaffold45240","Scaffold45241","Scaffold45242","Scaffold45243","Scaffold45244","Scaffold45245","Scaffold45246","Scaffold45247","Scaffold45248","Scaffold45249"]},"scaffold70945":{"prefix":[],"exact":[["Scaffold70945",201,"Scaffold70945",null,0,201,20000]]},"scaffold49152":{"prefix":[],"exact":[["Scaffold49152",304,"Scaffold49152",null,0,304,20000]]},"scaffold51666":{"prefix":[],"exact":[["Scaffold51666",289,"Scaffold51666",null,0,289,20000]]},"scaffold16409":{"exact":[["Scaffold16409",856,"Scaffold16409",null,0,856,20000]],"prefix":[]},"scaffold34627":{"exact":[["Scaffold34627",426,"Scaffold34627",null,0,426,20000]],"prefix":[]},"scaffold60234":{"exact":[["Scaffold60234",245,"Scaffold60234",null,0,245,20000]],"prefix":[]},"scaffold7829":{"prefix":[],"exact":[["Scaffold7829",2448,"Scaffold7829",null,0,2448,20000]]},"scaffold14362":{"exact":[["Scaffold14362",1980,"Scaffold14362",null,0,1980,20000]],"prefix":[]}}