{"scaffold47432":{"exact":[["Scaffold47432",315,"Scaffold47432",null,0,315,20000]],"prefix":[]},"scaffold22473":{"prefix":[],"exact":[["Scaffold22473",640,"Scaffold22473",null,0,640,20000]]},"scaffold59185":{"exact":[["Scaffold59185",250,"Scaffold59185",null,0,250,20000]],"prefix":[]},"scaffold33564":{"exact":[["Scaffold33564",439,"Scaffold33564",null,0,439,20000]],"prefix":[]},"scaffold3667":{"prefix":["Scaffold36670","Scaffold36671","Scaffold36672","Scaffold36673","Scaffold36674","Scaffold36675","Scaffold36676","Scaffold36677","Scaffold36678","Scaffold36679"],"exact":[["Scaffold3667",8521,"Scaffold3667",null,0,8521,20000]]},"scaffold18169":{"exact":[["Scaffold18169",778,"Scaffold18169",null,0,778,20000]],"prefix":[]},"scaffold67177":{"exact":[["Scaffold67177",215,"Scaffold67177",null,0,215,20000]],"prefix":[]},"scaffold45359":{"exact":[["Scaffold45359",330,"Scaffold45359",null,0,330,20000]],"prefix":[]},"scaffold20318":{"exact":[["Scaffold20318",701,"Scaffold20318",null,0,701,20000]],"prefix":[]},"scaffold55828":{"prefix":[],"exact":[["Scaffold55828",266,"Scaffold55828",null,0,266,20000]]},"scaffold30869":{"prefix":[],"exact":[["Scaffold30869",473,"Scaffold30869",null,0,473,20000]]},"scaffold56525":{"prefix":[],"exact":[["Scaffold56525",263,"Scaffold56525",null,0,263,20000]]},"scaffold48092":{"prefix":[],"exact":[["Scaffold48092",311,"Scaffold48092",null,0,311,20000]]},"scaffold60992":{"exact":[["Scaffold60992",242,"Scaffold60992",null,0,242,20000]],"prefix":[]},"scaffold13021":{"prefix":[],"exact":[["Scaffold13021",1098,"Scaffold13021",null,0,1098,20000]]}}