{"scaffold38497":{"exact":[["Scaffold38497",386,"Scaffold38497",null,0,386,20000]],"prefix":[]},"scaffold60929":{"exact":[["Scaffold60929",242,"Scaffold60929",null,0,242,20000]],"prefix":[]},"scaffold26120":{"prefix":[],"exact":[["Scaffold26120",554,"Scaffold26120",null,0,554,20000]]},"scaffold70258":{"prefix":[],"exact":[["Scaffold70258",203,"Scaffold70258",null,0,203,20000]]},"scaffold55893":{"prefix":[],"exact":[["Scaffold55893",266,"Scaffold55893",null,0,266,20000]]},"scaffold63424":{"exact":[["Scaffold63424",231,"Scaffold63424",null,0,231,20000]],"prefix":[]},"scaffold17572":{"prefix":[],"exact":[["Scaffold17572",801,"Scaffold17572",null,0,801,20000]]},"scaffold52076":{"exact":[["Scaffold52076",287,"Scaffold52076",null,0,287,20000]],"prefix":[]},"scaffold47489":{"prefix":[],"exact":[["Scaffold47489",315,"Scaffold47489",null,0,315,20000]]},"scaffold15219":{"exact":[["Scaffold15219",923,"Scaffold15219",null,0,923,20000]],"prefix":[]},"scaffold48029":{"prefix":[],"exact":[["Scaffold48029",311,"Scaffold48029",null,0,311,20000]]},"scaffold6952":{"prefix":["Scaffold69520","Scaffold69521","Scaffold69522","Scaffold69523","Scaffold69524","Scaffold69525","Scaffold69526","Scaffold69527","Scaffold69528","Scaffold69529"],"exact":[["Scaffold6952",2975,"Scaffold6952",null,0,2975,20000]]},"scaffold29580":{"exact":[["Scaffold29580",491,"Scaffold29580",null,0,491,20000]],"prefix":[]},"scaffold7334":{"exact":[["Scaffold7334",3723,"Scaffold7334",null,0,3723,20000]],"prefix":[]},"scaffold44984":{"exact":[["Scaffold44984",333,"Scaffold44984",null,0,333,20000]],"prefix":[]},"scaffold37037":{"prefix":[],"exact":[["Scaffold37037",401,"Scaffold37037",null,0,401,20000]]},"scaffold818":{"prefix":["Scaffold8180","Scaffold8181","Scaffold8182","Scaffold8183","Scaffold8184","Scaffold8185","Scaffold8186","Scaffold8187","Scaffold8188","Scaffold8189"],"exact":[["Scaffold818",52814,"Scaffold818",null,0,52814,20000]]},"scaffold8794":{"exact":[["Scaffold8794",3001,"Scaffold8794",null,0,3001,20000]],"prefix":[]},"scaffold43161":{"prefix":[],"exact":[["Scaffold43161",347,"Scaffold43161",null,0,347,20000]]}}