{"scaffold15024":{"prefix":[],"exact":[["Scaffold15024",936,"Scaffold15024",null,0,936,20000]]},"scaffold19989":{"prefix":[],"exact":[["Scaffold19989",711,"Scaffold19989",null,0,711,20000]]},"scaffold68751":{"exact":[["Scaffold68751",209,"Scaffold68751",null,0,209,20000]],"prefix":[]},"scaffold59303":{"exact":[["Scaffold59303",250,"Scaffold59303",null,0,250,20000]],"prefix":[]},"scaffold58965":{"prefix":[],"exact":[["Scaffold58965",251,"Scaffold58965",null,0,251,20000]]},"scaffold49872":{"exact":[["Scaffold49872",300,"Scaffold49872",null,0,300,20000]],"prefix":[]},"scaffold41437":{"exact":[["Scaffold41437",360,"Scaffold41437",null,0,360,20000]],"prefix":[]},"scaffold70065":{"prefix":[],"exact":[["Scaffold70065",204,"Scaffold70065",null,0,204,20000]]},"scaffold63619":{"prefix":[],"exact":[["Scaffold63619",230,"Scaffold63619",null,0,230,20000]]},"scaffold66997":{"exact":[["Scaffold66997",216,"Scaffold66997",null,0,216,20000]],"prefix":[]},"scaffold61172":{"prefix":[],"exact":[["Scaffold61172",241,"Scaffold61172",null,0,241,20000]]},"scaffold31089":{"prefix":[],"exact":[["Scaffold31089",470,"Scaffold31089",null,0,470,20000]]},"scaffold7109":{"prefix":["Scaffold71090","Scaffold71091","Scaffold71092","Scaffold71093","Scaffold71094","Scaffold71095","Scaffold71096","Scaffold71097","Scaffold71098","Scaffold71099"],"exact":[["Scaffold7109",3866,"Scaffold7109",null,0,3866,20000]]},"scaffold24476":{"exact":[["Scaffold24476",591,"Scaffold24476",null,0,591,20000]],"prefix":[]},"scaffold5662":{"prefix":["Scaffold56620","Scaffold56621","Scaffold56622","Scaffold56623","Scaffold56624","Scaffold56625","Scaffold56626","Scaffold56627","Scaffold56628","Scaffold56629"],"exact":[["Scaffold5662",4055,"Scaffold5662",null,0,4055,20000]]},"scaffold35561":{"prefix":[],"exact":[["Scaffold35561",359,"Scaffold35561",null,0,359,20000]]},"scaffold50520":{"exact":[["Scaffold50520",296,"Scaffold50520",null,0,296,20000]],"prefix":[]},"scaffold48214":{"prefix":[],"exact":[["Scaffold48214",310,"Scaffold48214",null,0,310,20000]]}}