{"scaffold32942":{"exact":[["Scaffold32942",446,"Scaffold32942",null,0,446,20000]],"prefix":[]},"scaffold67737":{"exact":[["Scaffold67737",213,"Scaffold67737",null,0,213,20000]],"prefix":[]},"scaffold68397":{"prefix":[],"exact":[["Scaffold68397",210,"Scaffold68397",null,0,210,20000]]},"scaffold23855":{"prefix":[],"exact":[["Scaffold23855",605,"Scaffold23855",null,0,605,20000]]},"scaffold56365":{"exact":[["Scaffold56365",264,"Scaffold56365",null,0,264,20000]],"prefix":[]},"scaffold46814":{"exact":[["Scaffold46814",320,"Scaffold46814",null,0,320,20000]],"prefix":[]},"scaffold22233":{"exact":[["Scaffold22233",645,"Scaffold22233",null,0,645,20000]],"prefix":[]},"scaffold57903":{"exact":[["Scaffold57903",256,"Scaffold57903",null,0,256,20000]],"prefix":[]},"scaffold13661":{"exact":[["Scaffold13661",1034,"Scaffold13661",null,0,1034,20000]],"prefix":[]},"scaffold33324":{"exact":[["Scaffold33324",442,"Scaffold33324",null,0,442,20000]],"prefix":[]},"scaffold18729":{"prefix":[],"exact":[["Scaffold18729",755,"Scaffold18729",null,0,755,20000]]},"scaffold3027":{"exact":[["Scaffold3027",10146,"Scaffold3027",null,0,10146,20000]],"prefix":["Scaffold30270","Scaffold30271","Scaffold30272","Scaffold30273","Scaffold30274","Scaffold30275","Scaffold30276","Scaffold30277","Scaffold30278","Scaffold30279"]},"scaffold45519":{"exact":[["Scaffold45519",329,"Scaffold45519",null,0,329,20000]],"prefix":[]},"scaffold20558":{"exact":[["Scaffold20558",693,"Scaffold20558",null,0,693,20000]],"prefix":[]},"scaffold47272":{"exact":[["Scaffold47272",317,"Scaffold47272",null,0,317,20000]],"prefix":[]},"scaffold17389":{"exact":[["Scaffold17389",809,"Scaffold17389",null,0,809,20000]],"prefix":[]}}