{"scaffold43088":{"exact":[["Scaffold43088",347,"Scaffold43088",null,0,347,20000]],"prefix":[]},"scaffold47560":{"prefix":[],"exact":[["Scaffold47560",314,"Scaffold47560",null,0,314,20000]]},"scaffold68485":{"exact":[["Scaffold68485",210,"Scaffold68485",null,0,210,20000]],"prefix":[]},"scaffold22521":{"prefix":[],"exact":[["Scaffold22521",638,"Scaffold22521",null,0,638,20000]]},"scaffold13173":{"prefix":[],"exact":[["Scaffold13173",1081,"Scaffold13173",null,0,1081,20000]]},"scaffold11618":{"exact":[["Scaffold11618",1266,"Scaffold11618",null,0,1266,20000]],"prefix":[]},"scaffold56477":{"exact":[["Scaffold56477",263,"Scaffold56477",null,0,263,20000]],"prefix":[]},"scaffold29469":{"prefix":[],"exact":[["Scaffold29469",493,"Scaffold29469",null,0,493,20000]]},"scaffold67025":{"exact":[["Scaffold67025",216,"Scaffold67025",null,0,216,20000]],"prefix":[]},"scaffold33436":{"exact":[["Scaffold33436",440,"Scaffold33436",null,0,440,20000]],"prefix":[]},"scaffold14996":{"exact":[["Scaffold14996",937,"Scaffold14996",null,0,937,20000]],"prefix":[]},"scaffold3735":{"prefix":["Scaffold37350","Scaffold37351","Scaffold37352","Scaffold37353","Scaffold37354","Scaffold37355","Scaffold37356","Scaffold37357","Scaffold37358","Scaffold37359"],"exact":[["Scaffold3735",6975,"Scaffold3735",null,0,6975,20000]]}}