{"scaffold22939":{"prefix":[],"exact":[["Scaffold22939",628,"Scaffold22939",null,0,628,20000]]},"scaffold57209":{"prefix":[],"exact":[["Scaffold57209",259,"Scaffold57209",null,0,259,20000]]},"scaffold9003":{"prefix":[],"exact":[["Scaffold9003",3019,"Scaffold9003",null,0,3019,20000]]},"scaffold17883":{"exact":[["Scaffold17883",788,"Scaffold17883",null,0,788,20000]],"prefix":[]},"scaffold39300":{"prefix":[],"exact":[["Scaffold39300",379,"Scaffold39300",null,0,379,20000]]},"scaffold21434":{"exact":[["Scaffold21434",668,"Scaffold21434",null,0,668,20000]],"prefix":[]},"scaffold32248":{"exact":[["Scaffold32248",455,"Scaffold32248",null,0,455,20000]],"prefix":[]},"scaffold55562":{"prefix":[],"exact":[["Scaffold55562",268,"Scaffold55562",null,0,268,20000]]},"scaffold47978":{"exact":[["Scaffold47978",312,"Scaffold47978",null,0,312,20000]],"prefix":[]},"scaffold44475":{"prefix":[],"exact":[["Scaffold44475",337,"Scaffold44475",null,0,337,20000]]},"scaffold19645":{"exact":[["Scaffold19645",723,"Scaffold19645",null,0,723,20000]],"prefix":[]},"scaffold28217":{"exact":[["Scaffold28217",514,"Scaffold28217",null,0,514,20000]],"prefix":[]},"scaffold30523":{"prefix":[],"exact":[["Scaffold30523",478,"Scaffold30523",null,0,478,20000]]},"scaffold38966":{"exact":[["Scaffold38966",382,"Scaffold38966",null,0,382,20000]],"prefix":[]},"scaffold10066":{"prefix":[],"exact":[["Scaffold10066",1565,"Scaffold10066",null,0,1565,20000]]},"scaffold64130":{"exact":[["Scaffold64130",228,"Scaffold64130",null,0,228,20000]],"prefix":[]},"scaffold29871":{"exact":[["Scaffold29871",487,"Scaffold29871",null,0,487,20000]],"prefix":[]}}