{"scaffold6409":{"prefix":["Scaffold64090","Scaffold64091","Scaffold64092","Scaffold64093","Scaffold64094","Scaffold64095","Scaffold64096","Scaffold64097","Scaffold64098","Scaffold64099"],"exact":[["Scaffold6409",4964,"Scaffold6409",null,0,4964,20000]]},"scaffold69251":{"prefix":[],"exact":[["Scaffold69251",207,"Scaffold69251",null,0,207,20000]]},"scaffold543":{"prefix":["Scaffold5430","Scaffold54300","Scaffold54301","Scaffold54302","Scaffold54303","Scaffold54304","Scaffold54305","Scaffold54306","Scaffold54307","Scaffold54308","Scaffold54309","Scaffold5431","Scaffold54310","Scaffold54311","Scaffold54312","Scaffold54313","Scaffold54314","Scaffold54315","Scaffold54316","Scaffold54317",{"hitLimit":1,"name":"too many matches"}],"exact":[["Scaffold543",82647,"Scaffold543",null,0,82647,20000]]},"scaffold62319":{"prefix":[],"exact":[["Scaffold62319",236,"Scaffold62319",null,0,236,20000]]},"scaffold17829":{"exact":[["Scaffold17829",790,"Scaffold17829",null,0,790,20000]],"prefix":[]},"scaffold4362":{"exact":[["Scaffold4362",7294,"Scaffold4362",null,0,7294,20000]],"prefix":["Scaffold43620","Scaffold43621","Scaffold43622","Scaffold43623","Scaffold43624","Scaffold43625","Scaffold43626","Scaffold43627","Scaffold43628","Scaffold43629"]},"scaffold49714":{"prefix":[],"exact":[["Scaffold49714",301,"Scaffold49714",null,0,301,20000]]},"scaffold51020":{"prefix":[],"exact":[["Scaffold51020",293,"Scaffold51020",null,0,293,20000]]},"scaffold68837":{"prefix":[],"exact":[["Scaffold68837",209,"Scaffold68837",null,0,209,20000]]},"scaffold30589":{"exact":[["Scaffold30589",477,"Scaffold30589",null,0,477,20000]],"prefix":[]},"scaffold22993":{"prefix":[],"exact":[["Scaffold22993",626,"Scaffold22993",null,0,626,20000]]},"scaffold5904":{"prefix":["Scaffold59040","Scaffold59041","Scaffold59042","Scaffold59043","Scaffold59044","Scaffold59045","Scaffold59046","Scaffold59047","Scaffold59048","Scaffold59049"],"exact":[["Scaffold5904",3810,"Scaffold5904",null,0,3810,20000]]},"scaffold34061":{"exact":[["Scaffold34061",433,"Scaffold34061",null,0,433,20000]],"prefix":[]},"scaffold33884":{"prefix":[],"exact":[["Scaffold33884",435,"Scaffold33884",null,0,435,20000]]},"scaffold14524":{"prefix":[],"exact":[["Scaffold14524",971,"Scaffold14524",null,0,971,20000]]},"scaffold58603":{"prefix":[],"exact":[["Scaffold58603",253,"Scaffold58603",null,0,253,20000]]},"scaffold60472":{"exact":[["Scaffold60472",244,"Scaffold60472",null,0,244,20000]],"prefix":[]},"scaffold40137":{"prefix":[],"exact":[["Scaffold40137",371,"Scaffold40137",null,0,371,20000]]},"scaffold25176":{"exact":[["Scaffold25176",575,"Scaffold25176",null,0,575,20000]],"prefix":[]}}