{"scaffold16461":{"prefix":[],"exact":[["Scaffold16461",853,"Scaffold16461",null,0,853,20000]]},"scaffold12189":{"prefix":[],"exact":[["Scaffold12189",1188,"Scaffold12189",null,0,1188,20000]]},"scaffold54980":{"prefix":[],"exact":[["Scaffold54980",271,"Scaffold54980",null,0,271,20000]]},"scaffold25758":{"prefix":[],"exact":[["Scaffold25758",562,"Scaffold25758",null,0,562,20000]]},"scaffold27033":{"prefix":[],"exact":[["Scaffold27033",536,"Scaffold27033",null,0,536,20000]]},"scaffold40719":{"prefix":[],"exact":[["Scaffold40719",367,"Scaffold40719",null,0,367,20000]]},"scaffold42072":{"prefix":[],"exact":[["Scaffold42072",355,"Scaffold42072",null,0,355,20000]]},"scaffold6227":{"prefix":["Scaffold62270","Scaffold62271","Scaffold62272","Scaffold62273","Scaffold62274","Scaffold62275","Scaffold62276","Scaffold62277","Scaffold62278","Scaffold62279"],"exact":[["Scaffold6227",3515,"Scaffold6227",null,0,3515,20000]]},"scaffold62537":{"prefix":[],"exact":[["Scaffold62537",235,"Scaffold62537",null,0,235,20000]]},"scaffold45897":{"exact":[["Scaffold45897",326,"Scaffold45897",null,0,326,20000]],"prefix":[]},"scaffold7841":{"exact":[["Scaffold7841",3442,"Scaffold7841",null,0,3442,20000]],"prefix":[]},"scaffold39584":{"prefix":[],"exact":[["Scaffold39584",376,"Scaffold39584",null,0,376,20000]]},"scaffold28493":{"prefix":[],"exact":[["Scaffold28493",509,"Scaffold28493",null,0,509,20000]]},"scaffold36124":{"exact":[["Scaffold36124",410,"Scaffold36124",null,0,410,20000]],"prefix":[]},"scaffold53165":{"exact":[["Scaffold53165",280,"Scaffold53165",null,0,280,20000]],"prefix":[]},"scaffold9687":{"prefix":[],"exact":[["Scaffold9687",2673,"Scaffold9687",null,0,2673,20000]]}}