{"scaffold44785":{"exact":[["Scaffold44785",335,"Scaffold44785",null,0,335,20000]],"prefix":[]},"scaffold58559":{"exact":[["Scaffold58559",253,"Scaffold58559",null,0,253,20000]],"prefix":[]},"scaffold60728":{"exact":[["Scaffold60728",243,"Scaffold60728",null,0,243,20000]],"prefix":[]},"scaffold55692":{"exact":[["Scaffold55692",267,"Scaffold55692",null,0,267,20000]],"prefix":[]},"scaffold16115":{"prefix":[],"exact":[["Scaffold16115",872,"Scaffold16115",null,0,872,20000]]},"scaffold27547":{"prefix":[],"exact":[["Scaffold27547",526,"Scaffold27547",null,0,526,20000]]},"scaffold8995":{"prefix":[],"exact":[["Scaffold8995",1923,"Scaffold8995",null,0,1923,20000]]},"scaffold4038":{"exact":[["Scaffold4038",7771,"Scaffold4038",null,0,7771,20000]],"prefix":["Scaffold40380","Scaffold40381","Scaffold40382","Scaffold40383","Scaffold40384","Scaffold40385","Scaffold40386","Scaffold40387","Scaffold40388","Scaffold40389"]},"scaffold10396":{"prefix":[],"exact":[["Scaffold10396",2489,"Scaffold10396",null,0,2489,20000]]},"scaffold53411":{"prefix":[],"exact":[["Scaffold53411",279,"Scaffold53411",null,0,279,20000]]},"scaffold6753":{"prefix":["Scaffold67530","Scaffold67531","Scaffold67532","Scaffold67533","Scaffold67534","Scaffold67535","Scaffold67536","Scaffold67537","Scaffold67538","Scaffold67539"],"exact":[["Scaffold6753",4306,"Scaffold6753",null,0,4306,20000]]},"scaffold42506":{"exact":[["Scaffold42506",352,"Scaffold42506",null,0,352,20000]],"prefix":[]},"scaffold619":{"prefix":["Scaffold6190","Scaffold61900","Scaffold61901","Scaffold61902","Scaffold61903","Scaffold61904","Scaffold61905","Scaffold61906","Scaffold61907","Scaffold61908","Scaffold61909","Scaffold6191","Scaffold61910","Scaffold61911","Scaffold61912","Scaffold61913","Scaffold61914","Scaffold61915","Scaffold61916","Scaffold61917",{"hitLimit":1,"name":"too many matches"}],"exact":[["Scaffold619",71993,"Scaffold619",null,0,71993,20000]]},"scaffold36450":{"prefix":[],"exact":[["Scaffold36450",407,"Scaffold36450",null,0,407,20000]]},"scaffold62043":{"prefix":[],"exact":[["Scaffold62043",237,"Scaffold62043",null,0,237,20000]]}}