{"scaffold9833":{"exact":[["Scaffold9833",1628,"Scaffold9833",null,0,1628,20000]],"prefix":[]},"scaffold22109":{"prefix":[],"exact":[["Scaffold22109",649,"Scaffold22109",null,0,649,20000]]},"scaffold70799":{"prefix":[],"exact":[["Scaffold70799",201,"Scaffold70799",null,0,201,20000]]},"scaffold1476":{"prefix":["Scaffold14760","Scaffold14761","Scaffold14762","Scaffold14763","Scaffold14764","Scaffold14765","Scaffold14766","Scaffold14767","Scaffold14768","Scaffold14769"],"exact":[["Scaffold1476",19817,"Scaffold1476",null,0,19817,20000]]},"scaffold47148":{"prefix":[],"exact":[["Scaffold47148",317,"Scaffold47148",null,0,317,20000]]},"scaffold54734":{"exact":[["Scaffold54734",272,"Scaffold54734",null,0,272,20000]],"prefix":[]},"scaffold20662":{"prefix":[],"exact":[["Scaffold20662",690,"Scaffold20662",null,0,690,20000]]},"scaffold31775":{"exact":[["Scaffold31775",461,"Scaffold31775",null,0,461,20000]],"prefix":[]},"scaffold45623":{"exact":[["Scaffold45623",328,"Scaffold45623",null,0,328,20000]],"prefix":[]},"scaffold8255":{"exact":[["Scaffold8255",2236,"Scaffold8255",null,0,2236,20000]],"prefix":[]},"scaffold11230":{"prefix":[],"exact":[["Scaffold11230",1326,"Scaffold11230",null,0,1326,20000]]},"scaffold64900":{"exact":[["Scaffold64900",224,"Scaffold64900",null,0,224,20000]],"prefix":[]},"scaffold65366":{"exact":[["Scaffold65366",222,"Scaffold65366",null,0,222,20000]],"prefix":[]},"scaffold29041":{"exact":[["Scaffold29041",499,"Scaffold29041",null,0,499,20000]],"prefix":[]},"scaffold38156":{"prefix":[],"exact":[["Scaffold38156",390,"Scaffold38156",null,0,390,20000]]},"scaffold10856":{"prefix":[],"exact":[["Scaffold10856",1395,"Scaffold10856",null,0,1395,20000]]},"scaffold18413":{"prefix":[],"exact":[["Scaffold18413",767,"Scaffold18413",null,0,767,20000]]}}