{"featureCount":26,"formatVersion":1,"histograms":{"meta":[{"arrayParams":{"chunkSize":10000,"length":6,"urlTemplate":"hist-2000-{Chunk}.json"},"basesPerBin":"2000"}],"stats":[{"basesPerBin":"2000","max":11,"mean":4.5}]},"intervals":{"classes":[{"attributes":["Start","End","Strand","Name","Seq_id"],"isArrayAttr":{}},{"attributes":["Start","End","Chunk"],"isArrayAttr":{"Sublist":1}}],"count":26,"lazyClass":1,"maxEnd":11208,"minStart":233,"nclist":[[0,233,313,1,"match_part","Scaffold2442"],[0,597,698,1,"match_part","Scaffold2442"],[0,1496,1572,1,"match_part","Scaffold2442"],[0,1898,1958,1,"match_part","Scaffold2442"],[0,2229,2315,1,"match_part","Scaffold2442"],[0,2904,3067,1,"match_part","Scaffold2442"],[0,3677,3833,1,"match_part","Scaffold2442"],[0,4464,4523,1,"match_part","Scaffold2442"],[0,5984,6133,1,"match_part","Scaffold2442"],[0,6136,6167,1,"match_part","Scaffold2442"],[0,6886,7014,1,"match_part","Scaffold2442"],[0,8136,8242,1,"match_part","Scaffold2442"],[0,8506,8634,1,"match_part","Scaffold2442"],[0,8845,9014,1,"match_part","Scaffold2442"],[0,9185,9224,1,"match_part","Scaffold2442"],[0,9225,9395,1,"match_part","Scaffold2442"],[0,9523,9582,1,"match_part","Scaffold2442"],[0,9584,9645,1,"match_part","Scaffold2442"],[0,9645,9719,1,"match_part","Scaffold2442"],[0,9722,9742,1,"match_part","Scaffold2442"],[0,9742,9749,1,"match_part","Scaffold2442"],[0,9749,9783,1,"match_part","Scaffold2442"],[0,10780,10843,1,"match_part","Scaffold2442"],[0,10844,10895,1,"match_part","Scaffold2442"],[0,10895,10912,1,"match_part","Scaffold2442"],[0,10914,11208,1,"match_part","Scaffold2442"]],"urlTemplate":"lf-{Chunk}.json"}}